{
  "title": "Maritime & Logistics University of Applied Sciences",
  "code": "MLUA",
  "description": {
    "type": "doc",
    "content": [
      {
        "type": "paragraph",
        "content": [
          {
            "type": "text",
            "text": "Netherlands Maritime University is a specialized training and educational institute for the maritime industry. NMU offers a Master of Science in Shipping and Transport, a management program for port and shipping professionals. This program is provided in Rotterdam, the Netherlands. STC-Group is a worldwide strategic combination of well-established education, training, research, consultancy and implementation service providers for the entire shipping, port, transport and logistics chain as well as for the port-related oil and chemical industry. STC-Group is renowned for its unique simulator park which forms a vital part of STC-Group's didactical model. Over 4,500 students are participating in vocational, Bachelor's and Master's programs. Home base of STC-Group is Rotterdam, the Netherlands. The STC-Group has developed knowledge hubs in Vietnam, Philippines, South-Africa, Oman and Brazil."
          }
        ]
      }
    ]
  },
  "type": "hogeschool",
  "brin_code": "29UK",
  "vendor": "hovi",
  "logoUrl": null,
  "hovi_id": "219",
  "phone": null,
  "email": null,
  "website": null,
  "main_location": {
    "hovi_id": "122",
    "name": "Maritime & Logistics University of Applied Sciences, vestiging Rotterdam",
    "street": "Lloydstraat 300",
    "zip": "3024 EA",
    "city": "ROTTERDAM",
    "country": "NL",
    "vendor": "hovi",
    "vestiging_SK123_id": "311",
    "url": "http://stc-group.nl",
    "brinvest": null
  },
  "products": [
    {
      "title": "Maritieme Techniek / Scheepsbouwkunde",
      "product_type": "croho_program",
      "product_level": "bachelor",
      "croho": "30032",
      "croho_name": "Maritieme Techniek / Scheepsbouwkunde",
      "croho_sector": "techniek",
      "credits": "240",
      "financing": "private",
      "vendor": "hovi",
      "location_hovi_id": "122",
      "organization_hovi_id": "219",
      "product_forms": [
        {
          "admission_description": null,
          "admission_selections": null,
          "admission_tests": null,
          "instruction_mode_description": null,
          "instruction_modes": [],
          "job_perspective": null,
          "lang_requirements_description": null,
          "numerus_fixus": false,
          "product_description": null,
          "product_result": null,
          "application_deadlines": [],
          "scholarships": []
        }
      ],
      "location": {
        "location_address": "Lloydstraat 300, 3024 EA, ROTTERDAM, NL",
        "location_components": {
          "geometry": {
            "coordinates": [
              4.461276799999999,
              51.9018252
            ],
            "type": "Point"
          },
          "properties": {
            "country": "NL",
            "postalCode": "3024 EA",
            "administrativeArea": "Zuid-Holland",
            "raw": [
              {
                "longText": "300",
                "shortText": "300",
                "types": [
                  "street_number"
                ]
              },
              {
                "longText": "Lloydstraat",
                "shortText": "Lloydstraat",
                "types": [
                  "route"
                ]
              },
              {
                "longText": "Delfshaven",
                "shortText": "Delfshaven",
                "types": [
                  "political",
                  "sublocality",
                  "sublocality_level_1"
                ]
              },
              {
                "longText": "Rotterdam",
                "shortText": "Rotterdam",
                "types": [
                  "locality",
                  "political"
                ]
              },
              {
                "longText": "Rotterdam",
                "shortText": "Rotterdam",
                "types": [
                  "administrative_area_level_2",
                  "political"
                ]
              },
              {
                "longText": "Zuid-Holland",
                "shortText": "ZH",
                "types": [
                  "administrative_area_level_1",
                  "political"
                ]
              },
              {
                "longText": "Netherlands",
                "shortText": "NL",
                "types": [
                  "country",
                  "political"
                ]
              },
              {
                "longText": "3024 EA",
                "shortText": "3024 EA",
                "types": [
                  "postal_code"
                ]
              }
            ],
            "displayName": "300",
            "formated": "Lloydstraat 300, 3024 EA Rotterdam, Netherlands",
            "viewport": {
              "south": 51.9003702697085,
              "west": 4.459750369708498,
              "north": 51.9030682302915,
              "east": 4.462448330291503
            }
          },
          "type": "Feature"
        },
        "location_data": {
          "type": "Point",
          "coordinates": [
            4.461276799999999,
            51.9018252
          ]
        },
        "hovi_id": "122",
        "name": "Maritime & Logistics University of Applied Sciences, vestiging Rotterdam",
        "street": "Lloydstraat 300",
        "zip": "3024 EA",
        "city": "ROTTERDAM",
        "country": "NL",
        "vendor": "hovi",
        "vestiging_SK123_id": "311",
        "url": "http://stc-group.nl",
        "brinvest": null
      }
    },
    {
      "title": "Diploma Management Studies Port, Shipping and Transport Management",
      "product_type": "course",
      "vendor": "hovi",
      "location_hovi_id": "122",
      "organization_hovi_id": "219",
      "product_forms": [
        {
          "admission_description": null,
          "admission_selections": null,
          "admission_tests": null,
          "instruction_mode_description": null,
          "instruction_modes": [
            "case_study",
            "computer_exercise",
            "excursion",
            "group_assignment",
            "group_discussion",
            "individual_assignment",
            "lecture",
            "literature_study",
            "oral_presentation",
            "portfolio",
            "practicum",
            "project",
            "research",
            "research_project",
            "research_proposal",
            "self_evaluation",
            "self_study",
            "working_group",
            "workshop"
          ],
          "job_perspective": null,
          "lang_requirements_description": null,
          "numerus_fixus": false,
          "product_description": null,
          "product_result": null,
          "application_deadlines": [
            {
              "application_deadline": null,
              "starting_date": "2013-09-02",
              "end_date": "2014-05-02"
            }
          ],
          "scholarships": [],
          "study_costs": [
            {
              "amount": "500",
              "description": {
                "type": "doc",
                "content": [
                  {
                    "type": "paragraph",
                    "content": [
                      {
                        "type": "text",
                        "text": "Type: visa, period: program"
                      }
                    ]
                  }
                ]
              }
            },
            {
              "amount": "8000",
              "description": {
                "type": "doc",
                "content": [
                  {
                    "type": "paragraph",
                    "content": [
                      {
                        "type": "text",
                        "text": "Type: cost_of_living, period: program"
                      }
                    ]
                  }
                ]
              }
            }
          ],
          "tuition_fees": [
            {
              "amount": "11195",
              "definitive": true,
              "description": null,
              "tuitionFeePeriod": "year",
              "tuitionFeeType": "non-eu",
              "year": 2013
            },
            {
              "amount": "11195",
              "definitive": true,
              "description": null,
              "tuitionFeePeriod": "year",
              "tuitionFeeType": "legal",
              "year": 2013
            },
            {
              "amount": "11195",
              "definitive": true,
              "description": null,
              "tuitionFeePeriod": "year",
              "tuitionFeeType": "legal",
              "year": 2012
            },
            {
              "amount": "11195",
              "definitive": true,
              "description": null,
              "tuitionFeePeriod": "year",
              "tuitionFeeType": "non-eu",
              "year": 2012
            }
          ]
        }
      ],
      "location": {
        "location_address": "Lloydstraat 300, 3024 EA, ROTTERDAM, NL",
        "location_components": {
          "geometry": {
            "coordinates": [
              4.461276799999999,
              51.9018252
            ],
            "type": "Point"
          },
          "properties": {
            "country": "NL",
            "postalCode": "3024 EA",
            "administrativeArea": "Zuid-Holland",
            "raw": [
              {
                "longText": "300",
                "shortText": "300",
                "types": [
                  "street_number"
                ]
              },
              {
                "longText": "Lloydstraat",
                "shortText": "Lloydstraat",
                "types": [
                  "route"
                ]
              },
              {
                "longText": "Delfshaven",
                "shortText": "Delfshaven",
                "types": [
                  "political",
                  "sublocality",
                  "sublocality_level_1"
                ]
              },
              {
                "longText": "Rotterdam",
                "shortText": "Rotterdam",
                "types": [
                  "locality",
                  "political"
                ]
              },
              {
                "longText": "Rotterdam",
                "shortText": "Rotterdam",
                "types": [
                  "administrative_area_level_2",
                  "political"
                ]
              },
              {
                "longText": "Zuid-Holland",
                "shortText": "ZH",
                "types": [
                  "administrative_area_level_1",
                  "political"
                ]
              },
              {
                "longText": "Netherlands",
                "shortText": "NL",
                "types": [
                  "country",
                  "political"
                ]
              },
              {
                "longText": "3024 EA",
                "shortText": "3024 EA",
                "types": [
                  "postal_code"
                ]
              }
            ],
            "displayName": "300",
            "formated": "Lloydstraat 300, 3024 EA Rotterdam, Netherlands",
            "viewport": {
              "south": 51.9003702697085,
              "west": 4.459750369708498,
              "north": 51.9030682302915,
              "east": 4.462448330291503
            }
          },
          "type": "Feature"
        },
        "location_data": {
          "type": "Point",
          "coordinates": [
            4.461276799999999,
            51.9018252
          ]
        },
        "hovi_id": "122",
        "name": "Maritime & Logistics University of Applied Sciences, vestiging Rotterdam",
        "street": "Lloydstraat 300",
        "zip": "3024 EA",
        "city": "ROTTERDAM",
        "country": "NL",
        "vendor": "hovi",
        "vestiging_SK123_id": "311",
        "url": "http://stc-group.nl",
        "brinvest": null
      }
    }
  ]
}